sphinxcontrib/__init__.py
sphinxcontrib/asyncio.py
sphinxcontrib_asyncio-0.3.0.dist-info/LICENSE
sphinxcontrib_asyncio-0.3.0.dist-info/METADATA
sphinxcontrib_asyncio-0.3.0.dist-info/WHEEL
sphinxcontrib_asyncio-0.3.0.dist-info/top_level.txt
sphinxcontrib_asyncio-0.3.0.dist-info/RECORD
