Metadata-Version: 2.1
Name: sphinxcontrib-asyncio
Version: 0.3.0
Summary: sphinx extension to support coroutines in markup
Home-page: https://github.com/aio-libs/sphinxcontrib-asyncio
Author: Andrew Svetlov
Author-email: andrew.svetlov@gmail.com
License: Apache 2
Platform: UNKNOWN
Classifier: Environment :: Plugins
Classifier: Framework :: AsyncIO
Classifier: Framework :: Sphinx :: Extension
Classifier: Intended Audience :: Developers
Classifier: License :: OSI Approved :: Apache Software License
Classifier: Programming Language :: Python
Classifier: Programming Language :: Python :: 3
Classifier: Programming Language :: Python :: 3.5
Classifier: Programming Language :: Python :: 3.6
Classifier: Programming Language :: Python :: 3.7
Classifier: Programming Language :: Python :: 3.8
Classifier: Programming Language :: Python :: 3.9
Classifier: Topic :: Documentation :: Sphinx
Classifier: Topic :: Software Development :: Documentation
Requires-Dist: sphinx (>=3.0)
